py_marktest/__init__.py
py_marktest/__main__.py
py_marktest/conftest.py
py_marktest/main.py
py_marktest/main_test.py
py_marktest/marktest.py
py_marktest/marktest_test.py
py_marktest-0.0.3.dist-info/LICENSE
py_marktest-0.0.3.dist-info/METADATA
py_marktest-0.0.3.dist-info/WHEEL
py_marktest-0.0.3.dist-info/top_level.txt
py_marktest-0.0.3.dist-info/RECORD
