Metadata-Version: 2.1
Name: py-marktest
Version: 0.0.3
Summary: A command line tool for testing Python snippets in markdown.
Author-email: Joseph Riddle <joeriddles10@gmail.com>
Project-URL: Homepage, https://github.com/joeriddles/py-marktest
Project-URL: Bug Tracker, https://github.com/joeriddles/py-marktest/issues
Classifier: License :: OSI Approved :: MIT License
Classifier: Programming Language :: Python :: 3
Classifier: Operating System :: OS Independent
Classifier: Topic :: Software Development :: Testing
Classifier: Topic :: Software Development :: Testing :: Unit
Classifier: Topic :: Text Processing :: Markup :: Markdown
Requires-Python: >=3.11
License-File: LICENSE
Requires-Dist: typer[all] ==0.9.0
Provides-Extra: dev
Requires-Dist: pytest >=7 ; extra == 'dev'
Requires-Dist: pytest-cov >=4 ; extra == 'dev'
